textsage/__init__.py
textsage/llm_utils.py
textsage/pandas_utils.py
textsage/setup_ollama.py
textsage/spark_utils.py
textsage-0.1.4.dist-info/licenses/LICENSE
textsage-0.1.4.dist-info/METADATA
textsage-0.1.4.dist-info/WHEEL
textsage-0.1.4.dist-info/top_level.txt
textsage-0.1.4.dist-info/RECORD
