Metadata-Version: 2.4
Name: textsage
Version: 0.1.4
Summary: Extract insights from text securely using local LLMs, now with enhanced support for Python, Pandas, and PySpark workflows.
Home-page: https://github.com/shivang98/textsage
Author: Shivang Agarwal
Author-email: Shivang Agarwal <shivangagarwal98@gmail.com>
License-Expression: MIT
Project-URL: Homepage, https://github.com/shivang98/textsage
Project-URL: Issues, https://github.com/shivang98/textsage/issues
Classifier: Programming Language :: Python :: 3
Classifier: Operating System :: OS Independent
Requires-Python: >=3.8
License-File: LICENSE
Requires-Dist: ollama
Provides-Extra: pyspark
Requires-Dist: pyspark; extra == "pyspark"
Provides-Extra: pandas
Requires-Dist: pandas; extra == "pandas"
Dynamic: author
Dynamic: home-page
Dynamic: license-file
Dynamic: requires-python
